setup.py
flv2faceimg/__init__.py
flv2faceimg/flv2faceimg.py
flv2faceimg0.0.1.egg-info/PKG-INFO
flv2faceimg0.0.1.egg-info/SOURCES.txt
flv2faceimg0.0.1.egg-info/dependency_links.txt
flv2faceimg0.0.1.egg-info/top_level.txt